klp.py
klp_logviewer-0.76.1.dist-info/LICENSE
klp_logviewer-0.76.1.dist-info/METADATA
klp_logviewer-0.76.1.dist-info/WHEEL
klp_logviewer-0.76.1.dist-info/entry_points.txt
klp_logviewer-0.76.1.dist-info/top_level.txt
klp_logviewer-0.76.1.dist-info/RECORD
