Metadata-Version: 2.2
Name: klp_logviewer
Version: 0.76.1
Summary: Lightweight CLI viewer for structured log files and streams (logfmt, JSONL and many others)
Author-email: Dirk Loss <mail@dirk-loss.de>
Project-URL: Documentation, https://github.com/dloss/klp
Project-URL: Repository, https://github.com/dloss/klp.git
Project-URL: Issues, https://github.com/dloss/klp/issues
Classifier: Programming Language :: Python :: 3
Classifier: License :: OSI Approved :: MIT License
Classifier: Operating System :: OS Independent
Requires-Python: >=3.7
License-File: LICENSE
Provides-Extra: test
Requires-Dist: pytest>=7.0; extra == "test"
Requires-Dist: pytest-cov>=4.0; extra == "test"
